Workbook

Sheet Master_Roster
A1: Employee_ID | B1: Full_Name | C1: Department | D1: Designation | E1: Employment_Type | F1: Base_Monthly_Salary_USD | G1: Hourly_Rate_USD | H1: Tax_Bracket | I1: Bank_Name | J1: Account_Number
A2: EMP-1001 | B2: Alexander Wright | C2: Engineering | D2: Senior Software Engineer | E2: Full-Time | F2: 8500 | G2: 0 | H2: 0.22 | I2: Chase Bank | J2: ACC-982143
A3: EMP-1002 | B3: Sophia Martinez | C3: Data Analytics | D3: Data Analyst | E3: Full-Time | F3: 6800 | G3: 0 | H3: 0.18 | I3: Bank of America | J3: ACC-451209
A4: EMP-1003 | B4: Liam Johnson | C4: HR | D4: HR Specialist | E4: Full-Time | F4: 5200 | G4: 0 | H4: 0.15 | I4: Wells Fargo | J4: ACC-773412
A5: EMP-1004 | B5: Olivia Smith | C5: Finance | D5: Financial Controller | E5: Full-Time | F5: 9100 | G5: 0 | H5: 0.25 | I5: Citibank | J5: ACC-129845
A6: EMP-1005 | B6: Noah Williams | C6: Marketing | D6: Growth Marketer | E6: Full-Time | F6: 6100 | G6: 0 | H6: 0.18 | I6: Chase Bank | J6: ACC-334920
A7: EMP-1006 | B7: Emma Brown | C7: Sales | D7: Account Executive | E7: Full-Time | F7: 7500 | G7: 0 | H7: 0.2 | I7: Bank of America | J7: ACC-556102
A8: EMP-1007 | B8: James Jones | C8: Operations | D8: Operations Manager | E8: Full-Time | F8: 7800 | G8: 0 | H8: 0.2 | I8: Wells Fargo | J8: ACC-889341
A9: EMP-1008 | B9: Ava Garcia | C9: Engineering | D9: Frontend Developer | E9: Contract | F9: 0 | G9: 45 | H9: 0.15 | I9: Citibank | J9: ACC-221983
A10: EMP-1009 | B10: William Miller | C10: Data Analytics | D10: Data Engineer | E10: Full-Time | F10: 8200 | G10: 0 | H10: 0.22 | I10: Chase Bank | J10: ACC-667104
A11: EMP-1010 | B11: Isabella Davis | C11: HR | D11: Recruiting Lead | E11: Full-Time | F11: 5900 | G11: 0 | H11: 0.15 | I11: Bank of America | J11: ACC-114592
A12: EMP-1011 | B12: Logan Rodriguez | C12: Finance | D12: Senior Accountant | E12: Full-Time | F12: 7200 | G12: 0 | H12: 0.2 | I12: Wells Fargo | J12: ACC-992340
A13: EMP-1012 | B13: Mia Martinez | C13: Marketing | D13: Content Strategist | E13: Contract | F13: 0 | G13: 35 | H13: 0.12 | I13: Citibank | J13: ACC-448102
... A101: EMP-1100 | B101: Alice Graham | C101: Data Analytics | D101: BI Analyst | E101: Full-Time | F101: 6900 | G101: 0 | H101: 0.18 | I101: Citibank | J101: ACC-221239

Sheet Matrix_Attendance_Tracker
A1: MONTHLY DYNAMIC MATRIX ATTENDANCE GRID
A3: Employee_ID | B3: Employee_Name | C3: 1 | D3: 2 | E3: 3 | F3: 4 | G3: 5 | H3: 6 | I3: 7 | J3: 8 | K3: 9 | L3: 10 | M3: 11 | N3: 12 | O3: 13 | P3: 14 | Q3: 15 | R3: 16 | S3: 17 | T3: 18 | U3: 19 | V3: 20 | W3: 21 | X3: 22 | Y3: 23 | Z3: 24 | AA3: 25 | AB3: 26 | AC3: 27 | AD3: 28 | AE3: 29 | AF3: 30 | AG3: 31 | AH3: Present_Count | AI3: Absent_Count | AJ3: Leave_Count
A4: EMP-1001 | B4: =VLOOKUP(A4, Master_Roster!A$2:B$102, 2, FALSE) -> Alexander Wright | C4: =CHOOSE(RANDBETWEEN(1, 3), "✔", " L", "❌") -> ❌ | D4: =CHOOSE(RANDBETWEEN(1, 3), "✔", " L", "❌") -> ❌ | E4: =CHOOSE(RANDBETWEEN(1, 3), "✔", " L", "❌") -> ❌ | F4: =CHOOSE(RANDBETWEEN(1, 3), "✔", " L", "❌") -> ❌ | G4: =CHOOSE(RANDBETWEEN(1, 3), "✔", " L", "❌") -> ❌ | H4: =CHOOSE(RANDBETWEEN(1, 3), "✔", " L", "❌") -> ❌ | I4: =CHOOSE(RANDBETWEEN(1, 3), "✔", " L", "❌") -> ✔ | J4: =CHOOSE(RANDBETWEEN(1, 3), "✔", " L", "❌") -> L | ... AG4: =CHOOSE(RANDBETWEEN(1, 3), "✔", " L", "❌") -> L | AH4: =COUNTIF(C4:AG4, "✔") -> 9 | AI4: =COUNTIF(C4:AG4, "❌") -> 15 | AJ4: =COUNTIF(C4:AG4, " L") -> 7
A5: EMP-1002 | B5: =VLOOKUP(A5, Master_Roster!A$2:B$102, 2, FALSE) -> Sophia Martinez | C5: =CHOOSE(RANDBETWEEN(1, 3), "✔", " L", "❌") -> ❌ | D5: =CHOOSE(RANDBETWEEN(1, 3), "✔", " L", "❌") -> ✔ | E5: =CHOOSE(RANDBETWEEN(1, 3), "✔", " L", "❌") -> ❌ | F5: =CHOOSE(RANDBETWEEN(1, 3), "✔", " L", "❌") -> ❌ | G5: =CHOOSE(RANDBETWEEN(1, 3), "✔", " L", "❌") -> ❌ | H5: =CHOOSE(RANDBETWEEN(1, 3), "✔", " L", "❌") -> ❌ | I5: =CHOOSE(RANDBETWEEN(1, 3), "✔", " L", "❌") -> ✔ | J5: =CHOOSE(RANDBETWEEN(1, 3), "✔", " L", "❌") -> L | ... AG5: =CHOOSE(RANDBETWEEN(1, 3), "✔", " L", "❌") -> ✔ | AH5: =COUNTIF(C5:AG5, "✔") -> 10 | AI5: =COUNTIF(C5:AG5, "❌") -> 11 | AJ5: =COUNTIF(C5:AG5, " L") -> 10
A6: EMP-1003 | B6: =VLOOKUP(A6, Master_Roster!A$2:B$102, 2, FALSE) -> Liam Johnson | C6: =CHOOSE(RANDBETWEEN(1, 3), "✔", " L", "❌") -> ❌ | D6: =CHOOSE(RANDBETWEEN(1, 3), "✔", " L", "❌") -> L | E6: =CHOOSE(RANDBETWEEN(1, 3), "✔", " L", "❌") -> ✔ | F6: =CHOOSE(RANDBETWEEN(1, 3), "✔", " L", "❌") -> ❌ | G6: =CHOOSE(RANDBETWEEN(1, 3), "✔", " L", "❌") -> ❌ | H6: =CHOOSE(RANDBETWEEN(1, 3), "✔", " L", "❌") -> ❌ | I6: =CHOOSE(RANDBETWEEN(1, 3), "✔", " L", "❌") -> ✔ | J6: =CHOOSE(RANDBETWEEN(1, 3), "✔", " L", "❌") -> L | ... AG6: =CHOOSE(RANDBETWEEN(1, 3), "✔", " L", "❌") -> ✔ | AH6: =COUNTIF(C6:AG6, "✔") -> 10 | AI6: =COUNTIF(C6:AG6, "❌") -> 12 | AJ6: =COUNTIF(C6:AG6, " L") -> 9
A7: EMP-1004 | B7: =VLOOKUP(A7, Master_Roster!A$2:B$102, 2, FALSE) -> Olivia Smith | C7: =CHOOSE(RANDBETWEEN(1, 3), "✔", " L", "❌") -> L | D7: =CHOOSE(RANDBETWEEN(1, 3), "✔", " L", "❌") -> ❌ | E7: =CHOOSE(RANDBETWEEN(1, 3), "✔", " L", "❌") -> ✔ | F7: =CHOOSE(RANDBETWEEN(1, 3), "✔", " L", "❌") -> ❌ | G7: =CHOOSE(RANDBETWEEN(1, 3), "✔", " L", "❌") -> L | H7: =CHOOSE(RANDBETWEEN(1, 3), "✔", " L", "❌") -> ✔ | I7: =CHOOSE(RANDBETWEEN(1, 3), "✔", " L", "❌") -> ✔ | J7: =CHOOSE(RANDBETWEEN(1, 3), "✔", " L", "❌") -> ✔ | ... AG7: =CHOOSE(RANDBETWEEN(1, 3), "✔", " L", "❌") -> ❌ | AH7: =COUNTIF(C7:AG7, "✔") -> 15 | AI7: =COUNTIF(C7:AG7, "❌") -> 6 | AJ7: =COUNTIF(C7:AG7, " L") -> 10
A8: EMP-1005 | B8: =VLOOKUP(A8, Master_Roster!A$2:B$102, 2, FALSE) -> Noah Williams | C8: =CHOOSE(RANDBETWEEN(1, 3), "✔", " L", "❌") -> ❌ | D8: =CHOOSE(RANDBETWEEN(1, 3), "✔", " L", "❌") -> ✔ | E8: =CHOOSE(RANDBETWEEN(1, 3), "✔", " L", "❌") -> ✔ | F8: =CHOOSE(RANDBETWEEN(1, 3), "✔", " L", "❌") -> L | G8: =CHOOSE(RANDBETWEEN(1, 3), "✔", " L", "❌") -> ✔ | H8: =CHOOSE(RANDBETWEEN(1, 3), "✔", " L", "❌") -> ❌ | I8: =CHOOSE(RANDBETWEEN(1, 3), "✔", " L", "❌") -> L | J8: =CHOOSE(RANDBETWEEN(1, 3), "✔", " L", "❌") -> ✔ | ... AG8: =CHOOSE(RANDBETWEEN(1, 3), "✔", " L", "❌") -> L | AH8: =COUNTIF(C8:AG8, "✔") -> 12 | AI8: =COUNTIF(C8:AG8, "❌") -> 11 | AJ8: =COUNTIF(C8:AG8, " L") -> 8
A9: EMP-1006 | B9: =VLOOKUP(A9, Master_Roster!A$2:B$102, 2, FALSE) -> Emma Brown | C9: =CHOOSE(RANDBETWEEN(1, 3), "✔", " L", "❌") -> ❌ | D9: =CHOOSE(RANDBETWEEN(1, 3), "✔", " L", "❌") -> L | E9: =CHOOSE(RANDBETWEEN(1, 3), "✔", " L", "❌") -> ✔ | F9: =CHOOSE(RANDBETWEEN(1, 3), "✔", " L", "❌") -> ✔ | G9: =CHOOSE(RANDBETWEEN(1, 3), "✔", " L", "❌") -> ✔ | H9: =CHOOSE(RANDBETWEEN(1, 3), "✔", " L", "❌") -> L | I9: =CHOOSE(RANDBETWEEN(1, 3), "✔", " L", "❌") -> ❌ | J9: =CHOOSE(RANDBETWEEN(1, 3), "✔", " L", "❌") -> L | ... AG9: =CHOOSE(RANDBETWEEN(1, 3), "✔", " L", "❌") -> ❌ | AH9: =COUNTIF(C9:AG9, "✔") -> 9 | AI9: =COUNTIF(C9:AG9, "❌") -> 13 | AJ9: =COUNTIF(C9:AG9, " L") -> 9
A10: EMP-1007 | B10: =VLOOKUP(A10, Master_Roster!A$2:B$102, 2, FALSE) -> James Jones | C10: =CHOOSE(RANDBETWEEN(1, 3), "✔", " L", "❌") -> ❌ | D10: =CHOOSE(RANDBETWEEN(1, 3), "✔", " L", "❌") -> L | E10: =CHOOSE(RANDBETWEEN(1, 3), "✔", " L", "❌") -> ✔ | F10: =CHOOSE(RANDBETWEEN(1, 3), "✔", " L", "❌") -> ❌ | G10: =CHOOSE(RANDBETWEEN(1, 3), "✔", " L", "❌") -> ✔ | H10: =CHOOSE(RANDBETWEEN(1, 3), "✔", " L", "❌") -> ✔ | I10: =CHOOSE(RANDBETWEEN(1, 3), "✔", " L", "❌") -> ✔ | J10: =CHOOSE(RANDBETWEEN(1, 3), "✔", " L", "❌") -> ✔ | ... AG10: =CHOOSE(RANDBETWEEN(1, 3), "✔", " L", "❌") -> ❌ | AH10: =COUNTIF(C10:AG10, "✔") -> 10 | AI10: =COUNTIF(C10:AG10, "❌") -> 13 | AJ10: =COUNTIF(C10:AG10, " L") -> 8
A11: EMP-1008 | B11: =VLOOKUP(A11, Master_Roster!A$2:B$102, 2, FALSE) -> Ava Garcia | C11: =CHOOSE(RANDBETWEEN(1, 3), "✔", " L", "❌") -> ✔ | D11: =CHOOSE(RANDBETWEEN(1, 3), "✔", " L", "❌") -> ✔ | E11: =CHOOSE(RANDBETWEEN(1, 3), "✔", " L", "❌") -> ✔ | F11: =CHOOSE(RANDBETWEEN(1, 3), "✔", " L", "❌") -> L | G11: =CHOOSE(RANDBETWEEN(1, 3), "✔", " L", "❌") -> L | H11: =CHOOSE(RANDBETWEEN(1, 3), "✔", " L", "❌") -> ✔ | I11: =CHOOSE(RANDBETWEEN(1, 3), "✔", " L", "❌") -> ❌ | J11: =CHOOSE(RANDBETWEEN(1, 3), "✔", " L", "❌") -> L | ... AG11: =CHOOSE(RANDBETWEEN(1, 3), "✔", " L", "❌") -> ❌ | AH11: =COUNTIF(C11:AG11, "✔") -> 12 | AI11: =COUNTIF(C11:AG11, "❌") -> 10 | AJ11: =COUNTIF(C11:AG11, " L") -> 9
A12: EMP-1009 | B12: =VLOOKUP(A12, Master_Roster!A$2:B$102, 2, FALSE) -> William Miller | C12: =CHOOSE(RANDBETWEEN(1, 3), "✔", " L", "❌") -> ✔ | D12: =CHOOSE(RANDBETWEEN(1, 3), "✔", " L", "❌") -> ✔ | E12: =CHOOSE(RANDBETWEEN(1, 3), "✔", " L", "❌") -> ✔ | F12: =CHOOSE(RANDBETWEEN(1, 3), "✔", " L", "❌") -> L | G12: =CHOOSE(RANDBETWEEN(1, 3), "✔", " L", "❌") -> L | H12: =CHOOSE(RANDBETWEEN(1, 3), "✔", " L", "❌") -> L | I12: =CHOOSE(RANDBETWEEN(1, 3), "✔", " L", "❌") -> ✔ | J12: =CHOOSE(RANDBETWEEN(1, 3), "✔", " L", "❌") -> L | ... AG12: =CHOOSE(RANDBETWEEN(1, 3), "✔", " L", "❌") -> ❌ | AH12: =COUNTIF(C12:AG12, "✔") -> 12 | AI12: =COUNTIF(C12:AG12, "❌") -> 4 | AJ12: =COUNTIF(C12:AG12, " L") -> 15
A13: EMP-1010 | B13: =VLOOKUP(A13, Master_Roster!A$2:B$102, 2, FALSE) -> Isabella Davis | C13: =CHOOSE(RANDBETWEEN(1, 3), "✔", " L", "❌") -> ✔ | D13: =CHOOSE(RANDBETWEEN(1, 3), "✔", " L", "❌") -> ❌ | E13: =CHOOSE(RANDBETWEEN(1, 3), "✔", " L", "❌") -> L | F13: =CHOOSE(RANDBETWEEN(1, 3), "✔", " L", "❌") -> L | G13: =CHOOSE(RANDBETWEEN(1, 3), "✔", " L", "❌") -> ✔ | H13: =CHOOSE(RANDBETWEEN(1, 3), "✔", " L", "❌") -> L | I13: =CHOOSE(RANDBETWEEN(1, 3), "✔", " L", "❌") -> ✔ | J13: =CHOOSE(RANDBETWEEN(1, 3), "✔", " L", "❌") -> L | ... AG13: =CHOOSE(RANDBETWEEN(1, 3), "✔", " L", "❌") -> ❌ | AH13: =COUNTIF(C13:AG13, "✔") -> 8 | AI13: =COUNTIF(C13:AG13, "❌") -> 11 | AJ13: =COUNTIF(C13:AG13, " L") -> 12
A14: EMP-1011 | B14: =VLOOKUP(A14, Master_Roster!A$2:B$102, 2, FALSE) -> Logan Rodriguez | C14: =CHOOSE(RANDBETWEEN(1, 3), "✔", " L", "❌") -> L | D14: =CHOOSE(RANDBETWEEN(1, 3), "✔", " L", "❌") -> ✔ | E14: =CHOOSE(RANDBETWEEN(1, 3), "✔", " L", "❌") -> L | F14: =CHOOSE(RANDBETWEEN(1, 3), "✔", " L", "❌") -> L | G14: =CHOOSE(RANDBETWEEN(1, 3), "✔", " L", "❌") -> L | H14: =CHOOSE(RANDBETWEEN(1, 3), "✔", " L", "❌") -> ❌ | I14: =CHOOSE(RANDBETWEEN(1, 3), "✔", " L", "❌") -> ✔ | J14: =CHOOSE(RANDBETWEEN(1, 3), "✔", " L", "❌") -> L | ... AG14: =CHOOSE(RANDBETWEEN(1, 3), "✔", " L", "❌") -> ❌ | AH14: =COUNTIF(C14:AG14, "✔") -> 11 | AI14: =COUNTIF(C14:AG14, "❌") -> 8 | AJ14: =COUNTIF(C14:AG14, " L") -> 12
A15: EMP-1012 | B15: =VLOOKUP(A15, Master_Roster!A$2:B$102, 2, FALSE) -> Mia Martinez | C15: =CHOOSE(RANDBETWEEN(1, 3), "✔", " L", "❌") -> ✔ | D15: =CHOOSE(RANDBETWEEN(1, 3), "✔", " L", "❌") -> ❌ | E15: =CHOOSE(RANDBETWEEN(1, 3), "✔", " L", "❌") -> ✔ | F15: =CHOOSE(RANDBETWEEN(1, 3), "✔", " L", "❌") -> L | G15: =CHOOSE(RANDBETWEEN(1, 3), "✔", " L", "❌") -> ❌ | H15: =CHOOSE(RANDBETWEEN(1, 3), "✔", " L", "❌") -> ✔ | I15: =CHOOSE(RANDBETWEEN(1, 3), "✔", " L", "❌") -> ✔ | J15: =CHOOSE(RANDBETWEEN(1, 3), "✔", " L", "❌") -> ❌ | ... AG15: =CHOOSE(RANDBETWEEN(1, 3), "✔", " L", "❌") -> ❌ | AH15: =COUNTIF(C15:AG15, "✔") -> 6 | AI15: =COUNTIF(C15:AG15, "❌") -> 13 | AJ15: =COUNTIF(C15:AG15, " L") -> 12
... A103: EMP-1100 | B103: =VLOOKUP(A103, Master_Roster!A$2:B$102, 2, FALSE) -> Alice Graham | C103: =CHOOSE(RANDBETWEEN(1, 3), "✔", " L", "❌") -> ❌ | D103: =CHOOSE(RANDBETWEEN(1, 3), "✔", " L", "❌") -> L | E103: =CHOOSE(RANDBETWEEN(1, 3), "✔", " L", "❌") -> ❌ | F103: =CHOOSE(RANDBETWEEN(1, 3), "✔", " L", "❌") -> L | G103: =CHOOSE(RANDBETWEEN(1, 3), "✔", " L", "❌") -> ❌ | H103: =CHOOSE(RANDBETWEEN(1, 3), "✔", " L", "❌") -> ✔ | I103: =CHOOSE(RANDBETWEEN(1, 3), "✔", " L", "❌") -> L | J103: =CHOOSE(RANDBETWEEN(1, 3), "✔", " L", "❌") -> L | ... AG103: =CHOOSE(RANDBETWEEN(1, 3), "✔", " L", "❌") -> ❌ | AH103: =COUNTIF(C103:AG103, "✔") -> 9 | AI103: =COUNTIF(C103:AG103, "❌") -> 10 | AJ103: =COUNTIF(C103:AG103, " L") -> 12
AK145: ✔ | AL145: ❌ | AM145: L
AK146: Present | AL146: Absent | AM146: Leave Half Day

Sheet Payroll_Calculator
A1: EXECUTIVE PAYROLL DISBURSEMENT & SLIP CALCULATOR
A3: Employee_ID | B3: Full_Name | C3: Department | D3: Employment_Type | E3: Base_Salary | F3: Days_Present | G3: Overtime_Pay | H3: Gross_Earnings | I3: Tax_Deductions | J3: Net_Disbursement
A4: =Master_Roster!A2 -> EMP-1001 | B4: =VLOOKUP(A4, Master_Roster!A$2:B$101, 2, FALSE) -> Alexander Wright | C4: =VLOOKUP(A4, Master_Roster!A$2:C$101, 3, FALSE) -> Engineering | D4: =VLOOKUP(A4, Master_Roster!A$2:E$101, 5, FALSE) -> Full-Time | E4: =VLOOKUP(A4, Master_Roster!A$2:F$101, 6, FALSE) -> 8500 | F4: =VLOOKUP(A4, Matrix_Attendance_Tracker!A$4:AJ$103, 34, FALSE) -> 9 | G4: =IF(D4="Full-Time", F4 * 25, F4 * 40) -> 225 | H4: =IF(D4="Full-Time", ROUND((E4/26)*F4 + G4, 2), ROUND(F4 * 160 + G4, 2)) -> 3167.31 | I4: =ROUND(H4 * VLOOKUP(A4, Master_Roster!A$2:H$101, 8, FALSE), 2) -> 696.81 | J4: =ROUND(H4 - I4, 2) -> 2470.5
A5: =Master_Roster!A3 -> EMP-1002 | B5: =VLOOKUP(A5, Master_Roster!A$2:B$101, 2, FALSE) -> Sophia Martinez | C5: =VLOOKUP(A5, Master_Roster!A$2:C$101, 3, FALSE) -> Data Analytics | D5: =VLOOKUP(A5, Master_Roster!A$2:E$101, 5, FALSE) -> Full-Time | E5: =VLOOKUP(A5, Master_Roster!A$2:F$101, 6, FALSE) -> 6800 | F5: =VLOOKUP(A5, Matrix_Attendance_Tracker!A$4:AJ$103, 34, FALSE) -> 10 | G5: =IF(D5="Full-Time", F5 * 25, F5 * 40) -> 250 | H5: =IF(D5="Full-Time", ROUND((E5/26)*F5 + G5, 2), ROUND(F5 * 160 + G5, 2)) -> 2865.38 | I5: =ROUND(H5 * VLOOKUP(A5, Master_Roster!A$2:H$101, 8, FALSE), 2) -> 515.77 | J5: =ROUND(H5 - I5, 2) -> 2349.61
A6: =Master_Roster!A4 -> EMP-1003 | B6: =VLOOKUP(A6, Master_Roster!A$2:B$101, 2, FALSE) -> Liam Johnson | C6: =VLOOKUP(A6, Master_Roster!A$2:C$101, 3, FALSE) -> HR | D6: =VLOOKUP(A6, Master_Roster!A$2:E$101, 5, FALSE) -> Full-Time | E6: =VLOOKUP(A6, Master_Roster!A$2:F$101, 6, FALSE) -> 5200 | F6: =VLOOKUP(A6, Matrix_Attendance_Tracker!A$4:AJ$103, 34, FALSE) -> 10 | G6: =IF(D6="Full-Time", F6 * 25, F6 * 40) -> 250 | H6: =IF(D6="Full-Time", ROUND((E6/26)*F6 + G6, 2), ROUND(F6 * 160 + G6, 2)) -> 2250 | I6: =ROUND(H6 * VLOOKUP(A6, Master_Roster!A$2:H$101, 8, FALSE), 2) -> 337.5 | J6: =ROUND(H6 - I6, 2) -> 1912.5
A7: =Master_Roster!A5 -> EMP-1004 | B7: =VLOOKUP(A7, Master_Roster!A$2:B$101, 2, FALSE) -> Olivia Smith | C7: =VLOOKUP(A7, Master_Roster!A$2:C$101, 3, FALSE) -> Finance | D7: =VLOOKUP(A7, Master_Roster!A$2:E$101, 5, FALSE) -> Full-Time | E7: =VLOOKUP(A7, Master_Roster!A$2:F$101, 6, FALSE) -> 9100 | F7: =VLOOKUP(A7, Matrix_Attendance_Tracker!A$4:AJ$103, 34, FALSE) -> 15 | G7: =IF(D7="Full-Time", F7 * 25, F7 * 40) -> 375 | H7: =IF(D7="Full-Time", ROUND((E7/26)*F7 + G7, 2), ROUND(F7 * 160 + G7, 2)) -> 5625 | I7: =ROUND(H7 * VLOOKUP(A7, Master_Roster!A$2:H$101, 8, FALSE), 2) -> 1406.25 | J7: =ROUND(H7 - I7, 2) -> 4218.75
A8: =Master_Roster!A6 -> EMP-1005 | B8: =VLOOKUP(A8, Master_Roster!A$2:B$101, 2, FALSE) -> Noah Williams | C8: =VLOOKUP(A8, Master_Roster!A$2:C$101, 3, FALSE) -> Marketing | D8: =VLOOKUP(A8, Master_Roster!A$2:E$101, 5, FALSE) -> Full-Time | E8: =VLOOKUP(A8, Master_Roster!A$2:F$101, 6, FALSE) -> 6100 | F8: =VLOOKUP(A8, Matrix_Attendance_Tracker!A$4:AJ$103, 34, FALSE) -> 12 | G8: =IF(D8="Full-Time", F8 * 25, F8 * 40) -> 300 | H8: =IF(D8="Full-Time", ROUND((E8/26)*F8 + G8, 2), ROUND(F8 * 160 + G8, 2)) -> 3115.38 | I8: =ROUND(H8 * VLOOKUP(A8, Master_Roster!A$2:H$101, 8, FALSE), 2) -> 560.77 | J8: =ROUND(H8 - I8, 2) -> 2554.61
A9: =Master_Roster!A7 -> EMP-1006 | B9: =VLOOKUP(A9, Master_Roster!A$2:B$101, 2, FALSE) -> Emma Brown | C9: =VLOOKUP(A9, Master_Roster!A$2:C$101, 3, FALSE) -> Sales | D9: =VLOOKUP(A9, Master_Roster!A$2:E$101, 5, FALSE) -> Full-Time | E9: =VLOOKUP(A9, Master_Roster!A$2:F$101, 6, FALSE) -> 7500 | F9: =VLOOKUP(A9, Matrix_Attendance_Tracker!A$4:AJ$103, 34, FALSE) -> 9 | G9: =IF(D9="Full-Time", F9 * 25, F9 * 40) -> 225 | H9: =IF(D9="Full-Time", ROUND((E9/26)*F9 + G9, 2), ROUND(F9 * 160 + G9, 2)) -> 2821.15 | I9: =ROUND(H9 * VLOOKUP(A9, Master_Roster!A$2:H$101, 8, FALSE), 2) -> 564.23 | J9: =ROUND(H9 - I9, 2) -> 2256.92
A10: =Master_Roster!A8 -> EMP-1007 | B10: =VLOOKUP(A10, Master_Roster!A$2:B$101, 2, FALSE) -> James Jones | C10: =VLOOKUP(A10, Master_Roster!A$2:C$101, 3, FALSE) -> Operations | D10: =VLOOKUP(A10, Master_Roster!A$2:E$101, 5, FALSE) -> Full-Time | E10: =VLOOKUP(A10, Master_Roster!A$2:F$101, 6, FALSE) -> 7800 | F10: =VLOOKUP(A10, Matrix_Attendance_Tracker!A$4:AJ$103, 34, FALSE) -> 10 | G10: =IF(D10="Full-Time", F10 * 25, F10 * 40) -> 250 | H10: =IF(D10="Full-Time", ROUND((E10/26)*F10 + G10, 2), ROUND(F10 * 160 + G10, 2)) -> 3250 | I10: =ROUND(H10 * VLOOKUP(A10, Master_Roster!A$2:H$101, 8, FALSE), 2) -> 650 | J10: =ROUND(H10 - I10, 2) -> 2600
A11: =Master_Roster!A9 -> EMP-1008 | B11: =VLOOKUP(A11, Master_Roster!A$2:B$101, 2, FALSE) -> Ava Garcia | C11: =VLOOKUP(A11, Master_Roster!A$2:C$101, 3, FALSE) -> Engineering | D11: =VLOOKUP(A11, Master_Roster!A$2:E$101, 5, FALSE) -> Contract | E11: =VLOOKUP(A11, Master_Roster!A$2:F$101, 6, FALSE) -> 0 | F11: =VLOOKUP(A11, Matrix_Attendance_Tracker!A$4:AJ$103, 34, FALSE) -> 12 | G11: =IF(D11="Full-Time", F11 * 25, F11 * 40) -> 480 | H11: =IF(D11="Full-Time", ROUND((E11/26)*F11 + G11, 2), ROUND(F11 * 160 + G11, 2)) -> 2400 | I11: =ROUND(H11 * VLOOKUP(A11, Master_Roster!A$2:H$101, 8, FALSE), 2) -> 360 | J11: =ROUND(H11 - I11, 2) -> 2040
A12: =Master_Roster!A10 -> EMP-1009 | B12: =VLOOKUP(A12, Master_Roster!A$2:B$101, 2, FALSE) -> William Miller | C12: =VLOOKUP(A12, Master_Roster!A$2:C$101, 3, FALSE) -> Data Analytics | D12: =VLOOKUP(A12, Master_Roster!A$2:E$101, 5, FALSE) -> Full-Time | E12: =VLOOKUP(A12, Master_Roster!A$2:F$101, 6, FALSE) -> 8200 | F12: =VLOOKUP(A12, Matrix_Attendance_Tracker!A$4:AJ$103, 34, FALSE) -> 12 | G12: =IF(D12="Full-Time", F12 * 25, F12 * 40) -> 300 | H12: =IF(D12="Full-Time", ROUND((E12/26)*F12 + G12, 2), ROUND(F12 * 160 + G12, 2)) -> 4084.62 | I12: =ROUND(H12 * VLOOKUP(A12, Master_Roster!A$2:H$101, 8, FALSE), 2) -> 898.62 | J12: =ROUND(H12 - I12, 2) -> 3186
A13: =Master_Roster!A11 -> EMP-1010 | B13: =VLOOKUP(A13, Master_Roster!A$2:B$101, 2, FALSE) -> Isabella Davis | C13: =VLOOKUP(A13, Master_Roster!A$2:C$101, 3, FALSE) -> HR | D13: =VLOOKUP(A13, Master_Roster!A$2:E$101, 5, FALSE) -> Full-Time | E13: =VLOOKUP(A13, Master_Roster!A$2:F$101, 6, FALSE) -> 5900 | F13: =VLOOKUP(A13, Matrix_Attendance_Tracker!A$4:AJ$103, 34, FALSE) -> 8 | G13: =IF(D13="Full-Time", F13 * 25, F13 * 40) -> 200 | H13: =IF(D13="Full-Time", ROUND((E13/26)*F13 + G13, 2), ROUND(F13 * 160 + G13, 2)) -> 2015.38 | I13: =ROUND(H13 * VLOOKUP(A13, Master_Roster!A$2:H$101, 8, FALSE), 2) -> 302.31 | J13: =ROUND(H13 - I13, 2) -> 1713.07
A14: =Master_Roster!A12 -> EMP-1011 | B14: =VLOOKUP(A14, Master_Roster!A$2:B$101, 2, FALSE) -> Logan Rodriguez | C14: =VLOOKUP(A14, Master_Roster!A$2:C$101, 3, FALSE) -> Finance | D14: =VLOOKUP(A14, Master_Roster!A$2:E$101, 5, FALSE) -> Full-Time | E14: =VLOOKUP(A14, Master_Roster!A$2:F$101, 6, FALSE) -> 7200 | F14: =VLOOKUP(A14, Matrix_Attendance_Tracker!A$4:AJ$103, 34, FALSE) -> 11 | G14: =IF(D14="Full-Time", F14 * 25, F14 * 40) -> 275 | H14: =IF(D14="Full-Time", ROUND((E14/26)*F14 + G14, 2), ROUND(F14 * 160 + G14, 2)) -> 3321.15 | I14: =ROUND(H14 * VLOOKUP(A14, Master_Roster!A$2:H$101, 8, FALSE), 2) -> 664.23 | J14: =ROUND(H14 - I14, 2) -> 2656.92
A15: =Master_Roster!A13 -> EMP-1012 | B15: =VLOOKUP(A15, Master_Roster!A$2:B$101, 2, FALSE) -> Mia Martinez | C15: =VLOOKUP(A15, Master_Roster!A$2:C$101, 3, FALSE) -> Marketing | D15: =VLOOKUP(A15, Master_Roster!A$2:E$101, 5, FALSE) -> Contract | E15: =VLOOKUP(A15, Master_Roster!A$2:F$101, 6, FALSE) -> 0 | F15: =VLOOKUP(A15, Matrix_Attendance_Tracker!A$4:AJ$103, 34, FALSE) -> 6 | G15: =IF(D15="Full-Time", F15 * 25, F15 * 40) -> 240 | H15: =IF(D15="Full-Time", ROUND((E15/26)*F15 + G15, 2), ROUND(F15 * 160 + G15, 2)) -> 1200 | I15: =ROUND(H15 * VLOOKUP(A15, Master_Roster!A$2:H$101, 8, FALSE), 2) -> 144 | J15: =ROUND(H15 - I15, 2) -> 1056
... A103: =Master_Roster!A101 -> EMP-1100 | B103: =VLOOKUP(A103, Master_Roster!A$2:B$101, 2, FALSE) -> Alice Graham | C103: =VLOOKUP(A103, Master_Roster!A$2:C$101, 3, FALSE) -> Data Analytics | D103: =VLOOKUP(A103, Master_Roster!A$2:E$101, 5, FALSE) -> Full-Time | E103: =VLOOKUP(A103, Master_Roster!A$2:F$101, 6, FALSE) -> 6900 | F103: =VLOOKUP(A103, Matrix_Attendance_Tracker!A$4:AJ$103, 34, FALSE) -> 9 | G103: =IF(D103="Full-Time", F103 * 25, F103 * 40) -> 225 | H103: =IF(D103="Full-Time", ROUND((E103/26)*F103 + G103, 2), ROUND(F103 * 160 + G103, 2)) -> 2613.46 | I103: =ROUND(H103 * VLOOKUP(A103, Master_Roster!A$2:H$101, 8, FALSE), 2) -> 470.42 | J103: =ROUND(H103 - I103, 2) -> 2143.04

Sheet Control_Dashboard
A1: ENTERPRISE ATTENDANCE & PAYROLL EXECUTIVE COMMAND CENTER | J1: SUBJECT: Enterprise Architecture Note — Interactive Simulation & Production Deployment Standards
A2: Real-Time Operational Intelligence & Multi-Period Controls
J3: As part of our high-ticket enterprise solution delivery, this workbook has been engineered with an interactive simulation layer designed to showcase real-time cross-sheet data mapping and multi-period reporting capabilities.
B4: Select Month | D4: Feburary
B5: Select Year | D5: 2018 | J5: To ensure full transparency during your evaluation of this prototype, the operational behavior of the workbook across its four integrated sheets is detailed below:
J6: 1. System-Wide Recalculation Behavior
A7: TOTAL ACTIVE STAFF | C7: AVG ATTENDANCE RATE | E7: TOTAL OVERTIME DAYS | G7: MONTHLY PAYROLL OUTFLOW | J7: Due to the active simulation engine implemented in this demonstration model, adjusting layout dimensions (such as row/column widths) or toggling period parameters will trigger standard Excel worksheet recalculations. This interactivity is intentionally maintained to provide a live, software-like experience when testing the dashboard dropdowns and period selectors.
J8: 2. Sheet-by-Sheet Impact Breakdown
A9: =COUNTA(Master_Roster!A$2:A$101) -> 100 | C9: =AVERAGE(Matrix_Attendance_Tracker!AH$4:AH$103)/31 -> 0.33580645 | E9: =SUM(Matrix_Attendance_Tracker!AI$4:AI$103) -> 1041 | G9: =SUM(Payroll_Calculator!J$4:J$103) -> 242719.98 | J9: Sheet 1: Master_Roster (Core Database)
J10: Behavior: 100% Static. As the primary centralized database containing master employee identification, corporate hierarchies, and baseline compensation tiers, this sheet remains completely unaffected by layout adjustments or simulation toggles, ensuring absolute data integrity.
J11: Sheet 2: Matrix_Attendance_Tracker (Operational Grid)
J12: Behavior: Dynamic Simulation Layer. Aside from unique Employee IDs and full names, the operational attendance tracking columns utilize randomized distribution logic to simulate varying monthly attendance patterns and allow real-time filter testing.
J13: Sheet 3: Payroll_Calculator (Automated Engine)
J14: Behavior: Downstream Calculation Layer. The final five financial columns (Days Present, Overtime Pay, Gross Earnings, Tax Withholdings & Net Disbursements) dynamically respond to changes originating from the attendance matrix, maintaining strict mathematical parity with active workforce inputs.
J15: Sheet 4: Control_Dashboard (Executive Command Center)
J16: Behavior: Aggregated Metric Display. The three primary financial and operational KPI cards (Average Attendance Rate, Total Overtime, and Total Monthly Payroll Outflow) dynamically reflect changes from the underlying calculation engines.
J17: 3. Purpose of Dynamic Simulation & Dropdown Interactivity
J18: The volatile random functions have been deliberately integrated into this prototype to enable live interactivity. When you select different months or years from the dashboard dropdown selectors, the system instantly recalculates downstream metrics, proving the seamless cross-sheet integration and responsiveness of the model. This guarantees that your team can evaluate filtering mechanics effortlessly during the review phase.
J19: 4. Production Deployment & Client Guarantee
J20: The volatile simulation functions utilized in this demonstration prototype are strictly exclusive to portfolio evaluation and interactive feature testing.
J21: For final client deployment, this prototype layer is completely removed and replaced with your verified historical records. Attendance records will be populated directly from verified HR check-ins or manual attendance inputs, resulting in a 100% static, deterministic, and audit-ready enterprise system tailored precisely to your operational standards.
AA61: January
AA62: Feburary | AB62: 2017
AA63: March | AB63: 2018
AA64: April | AB64: 2019
AA65: May | AB65: 2020
AA66: June | AB66: 2021
AA67: July | AB67: 2022
AA68: August | AB68: 2023
AA69: September | AB69: 2024
AA70: October | AB70: 2025
AA71: November | AB71: 2026
AA72: December
